mypkg/__init__.py
mypkg/mysqlutils.py
mypkg/test.py
mypkg_zmhus-0.0.5.dist-info/LICENSE
mypkg_zmhus-0.0.5.dist-info/METADATA
mypkg_zmhus-0.0.5.dist-info/WHEEL
mypkg_zmhus-0.0.5.dist-info/top_level.txt
mypkg_zmhus-0.0.5.dist-info/RECORD
