Metadata-Version: 2.1
Name: mypkg-zmhus
Version: 0.0.5
Summary: just for test
Home-page: UNKNOWN
Author: zmhus
Author-email: zmhus@foxmail.com
License: UNKNOWN
Platform: UNKNOWN
